beancount_lsb/__init__.py
beancount_lsb/lsbimporter.py
beancount_lsb-1.0.0.dist-info/licenses/LICENSE.txt
beancount_lsb-1.0.0.dist-info/METADATA
beancount_lsb-1.0.0.dist-info/WHEEL
beancount_lsb-1.0.0.dist-info/top_level.txt
beancount_lsb-1.0.0.dist-info/RECORD
