Metadata-Version: 2.4
Name: beancount-lsb
Version: 1.0.0
Summary: Beancount Importer for LSB CSV exports
Author: Jonas Andersen
License: MIT License
Project-URL: Repository, https://github.com/joandrsn/beancount-lsb
Keywords: banking,beancount,cli-accounting,finance
Classifier: Development Status :: 4 - Beta
Classifier: Environment :: Console
Classifier: Environment :: Plugins
Classifier: Intended Audience :: End Users/Desktop
Classifier: Intended Audience :: Financial and Insurance Industry
Classifier: License :: OSI Approved :: MIT License
Classifier: Programming Language :: Python :: 3
Classifier: Programming Language :: Python :: 3.11
Classifier: Programming Language :: Python :: 3.12
Classifier: Programming Language :: Python :: 3.13
Classifier: Programming Language :: Python :: 3 :: Only
Classifier: Topic :: Office/Business :: Financial
Classifier: Topic :: Office/Business :: Financial :: Accounting
Requires-Python: >=3.11
License-File: LICENSE.txt
Requires-Dist: beangulp>=0.2.0
Dynamic: license-file
